.gitignore
setup.py
.idea/Overwatch-User-API-master.iml
.idea/OverwatchUserDirectory.iml
.idea/discord.xml
.idea/misc.xml
.idea/modules.xml
.idea/vcs.xml
.idea/workspace.xml
.idea/inspectionProfiles/Project_Default.xml
.idea/inspectionProfiles/profiles_settings.xml
OverwatchUserDirectory/__init__.py
OverwatchUserDirectory.egg-info/PKG-INFO
OverwatchUserDirectory.egg-info/SOURCES.txt
OverwatchUserDirectory.egg-info/dependency_links.txt
OverwatchUserDirectory.egg-info/requires.txt
OverwatchUserDirectory.egg-info/top_level.txt
OverwatchUserDirectory/ratings/Ratings.py
OverwatchUserDirectory/ratings/__init__.py
OverwatchUserDirectory/ratings/rate.py
OverwatchUserDirectory/stats/Lhero.py
OverwatchUserDirectory/stats/__init__.py
OverwatchUserDirectory/stats/careerstats.py
OverwatchUserDirectory/stats/stats.py
OverwatchUserDirectory/stats/Heroes/__init__.py
OverwatchUserDirectory/stats/Heroes/Hero/__init__.py
OverwatchUserDirectory/stats/Heroes/Hero/assists.py
OverwatchUserDirectory/stats/Heroes/Hero/average.py
OverwatchUserDirectory/stats/Heroes/Hero/best.py
OverwatchUserDirectory/stats/Heroes/Hero/combat.py
OverwatchUserDirectory/stats/Heroes/Hero/game.py
OverwatchUserDirectory/stats/Heroes/Hero/hero.py
OverwatchUserDirectory/stats/Heroes/Hero/heroSpecific.py
OverwatchUserDirectory/stats/Heroes/Hero/matchAwards.py
OverwatchUserDirectory/stats/Heroes/Hero/miscellaneous.py
OverwatchUserDirectory/stats/allHeroes/AllHeroes.py
OverwatchUserDirectory/stats/allHeroes/__init__.py
OverwatchUserDirectory/stats/allHeroes/assists.py
OverwatchUserDirectory/stats/allHeroes/average.py
OverwatchUserDirectory/stats/allHeroes/best.py
OverwatchUserDirectory/stats/allHeroes/combat.py
OverwatchUserDirectory/stats/allHeroes/game.py
OverwatchUserDirectory/stats/allHeroes/matchAwards.py
OverwatchUserDirectory/stats/allHeroes/miscellaneous.py
test/test.py